hx_secret_keeper/__init__.py
hx_secret_keeper/aws_secret.py
hx_secret_keeper/azure_secret.py
hx_secret_keeper/base_secret.py
hx_secret_keeper/get_secret.py
hx_secret_keeper/secret_factory.py
hx_secret_keeper-0.1.2.dist-info/WHEEL
hx_secret_keeper-0.1.2.dist-info/METADATA
hx_secret_keeper-0.1.2.dist-info/RECORD
