Metadata-Version: 2.1
Name: hx-secret-keeper
Version: 0.1.2
Summary: 
Author: Sujay S Kumar
Author-email: sujay@hypersonix.ai
Requires-Python: >=3.6,<4.0
Classifier: Programming Language :: Python :: 3
Classifier: Programming Language :: Python :: 3.6
Classifier: Programming Language :: Python :: 3.7
Classifier: Programming Language :: Python :: 3.8
Requires-Dist: aws_secretsmanager_caching (>=1.1.1,<2.0.0)
Requires-Dist: boto3 (>=1.17.23,<2.0.0)
